odoo/addons/graphql_base/README.rst
odoo/addons/graphql_base/__init__.py
odoo/addons/graphql_base/__manifest__.py
odoo/addons/graphql_base/types.py
odoo/addons/graphql_base/controllers/__init__.py
odoo/addons/graphql_base/controllers/main.py
odoo/addons/graphql_base/i18n/graphql_base.pot
odoo/addons/graphql_base/i18n/it.po
odoo/addons/graphql_base/readme/DESCRIPTION.rst
odoo/addons/graphql_base/readme/USAGE.rst
odoo/addons/graphql_base/static/description/icon.png
odoo/addons/graphql_base/static/description/index.html
odoo/addons/graphql_base/views/graphiql.xml
odoo14_addon_graphql_base-14.0.1.0.1.dev5.dist-info/METADATA
odoo14_addon_graphql_base-14.0.1.0.1.dev5.dist-info/WHEEL
odoo14_addon_graphql_base-14.0.1.0.1.dev5.dist-info/top_level.txt
odoo14_addon_graphql_base-14.0.1.0.1.dev5.dist-info/RECORD
