Metadata-Version: 2.1
Name: odoo14-addon-graphql_base
Version: 14.0.1.0.1.dev5
Summary: Base GraphQL/GraphiQL controller
Home-page: https://github.com/OCA/rest-framework
Author: ACSONE SA/NV,Odoo Community Association (OCA)
Author-email: support@odoo-community.org
License: LGPL-3
Classifier: Programming Language :: Python
Classifier: Framework :: Odoo
Classifier: Framework :: Odoo :: 14.0
Classifier: License :: OSI Approved :: GNU Lesser General Public License v3 (LGPLv3)
Classifier: Development Status :: 5 - Production/Stable
Requires-Python: >=3.6
Requires-Dist: graphene
Requires-Dist: graphql-server
Requires-Dist: odoo<14.1dev,>=14.0a
